hypothesis_numpy/__init__.py
hypothesis_numpy/hypothesis_numpy.py
hypothesis_numpy2-0.1.2.dist-info/METADATA
hypothesis_numpy2-0.1.2.dist-info/WHEEL
hypothesis_numpy2-0.1.2.dist-info/top_level.txt
hypothesis_numpy2-0.1.2.dist-info/RECORD
